easypygamewidgets/__init__.py
easypygamewidgets/button.py
easypygamewidgets/entry.py
easypygamewidgets/label.py
easypygamewidgets/misc.py
easypygamewidgets/screen.py
easypygamewidgets/slider.py
easypygamewidgets-1.1.2.dist-info/licenses/LICENSE
easypygamewidgets-1.1.2.dist-info/METADATA
easypygamewidgets-1.1.2.dist-info/WHEEL
easypygamewidgets-1.1.2.dist-info/top_level.txt
easypygamewidgets-1.1.2.dist-info/RECORD
