Metadata-Version: 2.4
Name: easypygamewidgets
Version: 1.1.2
Summary: Create GUIs for pygame.
Home-page: https://github.com/PizzaPost/pywidgets 
Author: PizzaPost
License-File: LICENSE
Requires-Dist: pygame
Requires-Dist: requests
Dynamic: author
Dynamic: description
Dynamic: description-content-type
Dynamic: home-page
Dynamic: license-file
Dynamic: requires-dist
Dynamic: summary
